birdhousebuilder.recipe.supervisor-0.3.6-py2.7-nspkg.pth
birdhousebuilder/recipe/supervisor/README.txt
birdhousebuilder/recipe/supervisor/__init__.py
birdhousebuilder/recipe/supervisor/program.conf
birdhousebuilder/recipe/supervisor/supervisord
birdhousebuilder/recipe/supervisor/supervisord.conf
birdhousebuilder/recipe/supervisor/tests/__init__.py
birdhousebuilder/recipe/supervisor/tests/test_docs.py
birdhousebuilder/recipe/supervisor/tests/test_doctests.py
birdhousebuilder.recipe.supervisor-0.3.6.dist-info/DESCRIPTION.rst
birdhousebuilder.recipe.supervisor-0.3.6.dist-info/METADATA
birdhousebuilder.recipe.supervisor-0.3.6.dist-info/RECORD
birdhousebuilder.recipe.supervisor-0.3.6.dist-info/WHEEL
birdhousebuilder.recipe.supervisor-0.3.6.dist-info/entry_points.txt
birdhousebuilder.recipe.supervisor-0.3.6.dist-info/metadata.json
birdhousebuilder.recipe.supervisor-0.3.6.dist-info/namespace_packages.txt
birdhousebuilder.recipe.supervisor-0.3.6.dist-info/pbr.json
birdhousebuilder.recipe.supervisor-0.3.6.dist-info/top_level.txt
