Metadata-Version: 2.0
Name: birdhousebuilder.recipe.supervisor
Version: 0.3.6
Summary: A Buildout recipe to install and configure supervisor for Anaconda.
Home-page: https://github.com/bird-house/birdhousebuilder.recipe.supervisor.git
Author: Birdhouse
Author-email: wps-dev at dkrz.de
License: Apache License 2
Keywords: buildout recipe supervisor birdhouse conda anaconda
Platform: UNKNOWN
Classifier: Framework :: Buildout
Classifier: Intended Audience :: Developers
Classifier: Topic :: Software Development :: Build Tools
Classifier: Topic :: Software Development :: Libraries :: Python Modules
Classifier: License :: OSI Approved :: BSD License
Requires-Dist: Mako
Requires-Dist: birdhousebuilder.recipe.conda (>=0.3.1)
Requires-Dist: setuptools
Requires-Dist: zc.buildout
Requires-Dist: zc.recipe.deployment (>=1.3.0)
Requires-Dist: zc.recipe.egg
Provides-Extra: tests
Requires-Dist: zc.buildout; extra == 'tests'
Requires-Dist: zope.testing; extra == 'tests'
